{
  "initial": {
    "user": {
      "fund": 10000,
      "stocks": [],
      "currentStock": {},
      "currentStockIndex": null,
      "canBuy": true,
      "canSell": false
    },
    "stocks": [
      {
        "title": "bmw",
        "price": 110
      },
      {
        "title": "google",
        "price": 200
      },
      {
        "title": "apple",
        "price": 250
      },
      {
        "title": "twitter",
        "price": 8
      }
    ],
    "currentStock": null,
    "isDataDropdown": false
  },
  "state": {
    "user": {
      "fund": 4320,
      "stocks": [
        {
          "title": "bmw",
          "price": 110,
          "quantity": 10
        },
        {
          "title": "google",
          "price": 200,
          "quantity": 10
        },
        {
          "title": "twitter",
          "price": 8,
          "quantity": 10
        },
        {
          "title": "apple",
          "price": 250,
          "quantity": 10
        }
      ],
      "currentStock": {},
      "currentStockIndex": 2,
      "canBuy": true,
      "canSell": false
    },
    "stocks": [
      {
        "title": "bmw",
        "price": 110
      },
      {
        "title": "google",
        "price": 200
      },
      {
        "title": "apple",
        "price": 250
      },
      {
        "title": "twitter",
        "price": 8
      }
    ],
    "currentStock": {
      "title": "apple",
      "price": 250
    }
  }
}
